afilter/__init__.py
afilter/async_server.py
afilter/server.py
afilter/version.py
afilter/protos/__init__.py
afilter/protos/afilter_pb2.py
afilter/protos/afilter_pb2_grpc.py
afilter/utils/__init__.py
afilter/utils/check_health.py
afilter/utils/transform.py
afilter-2.3.2.dist-info/METADATA
afilter-2.3.2.dist-info/WHEEL
afilter-2.3.2.dist-info/top_level.txt
afilter-2.3.2.dist-info/RECORD
