Metadata-Version: 2.1
Name: afilter
Version: 2.3.2
Summary: UNKNOWN
Home-page: UNKNOWN
Author: WJG
Author-email: wangjiangong2018@ia.ac.cn
License: Apache
Platform: UNKNOWN
Requires-Python: >=3.6
Requires-Dist: argparse
Requires-Dist: numpy
Requires-Dist: grpcio
Requires-Dist: pillow
Requires-Dist: nvidia-pyindex
Requires-Dist: tritonclient[all]
